{
	"$schema": "http://schema.management.azure.com/schemas/2015-01-01/deploymentTemplate.json#",
	"contentVersion": "1.0.0.0",
	"parameters": {
		"factoryName": {
			"type": "string",
			"metadata": "Data Factory name",
			"defaultValue": "NCS-LEAP-DataMovement"
		}
	},
	"variables": {
		"factoryId": "[concat('Microsoft.DataFactory/factories/', parameters('factoryName'))]"
	},
	"resources": [
		{
			"name": "[concat(parameters('factoryName'), '/S3LeapDataSet_Cloud2_File')]",
			"type": "Microsoft.DataFactory/factories/datasets",
			"apiVersion": "2018-06-01",
			"properties": {
				"linkedServiceName": {
					"referenceName": "Leap_AmazonS3",
					"type": "LinkedServiceReference"
				},
				"parameters": {
					"filename": {
						"type": "string"
					}
				},
				"folder": {
					"name": "FileConnection"
				},
				"annotations": [],
				"type": "Binary",
				"typeProperties": {
					"location": {
						"type": "AmazonS3Location",
						"bucketName": "leapdata-tas",
						"folderPath": "LEAP/Cloud2",
						"fileName": {
							"value": "@dataset().filename",
							"type": "Expression"
						}
					}
				}
			},
			"dependsOn": []
		},
		{
			"name": "[concat(parameters('factoryName'), '/S3LeapDataSet_Cloud2_Folder')]",
			"type": "Microsoft.DataFactory/factories/datasets",
			"apiVersion": "2018-06-01",
			"properties": {
				"linkedServiceName": {
					"referenceName": "Leap_AmazonS3",
					"type": "LinkedServiceReference"
				},
				"folder": {
					"name": "FileConnection"
				},
				"annotations": [],
				"type": "Binary",
				"typeProperties": {
					"location": {
						"type": "AmazonS3Location",
						"bucketName": "leapdata-tas",
						"folderPath": "LEAP/Cloud2"
					}
				}
			},
			"dependsOn": []
		},
		{
			"name": "[concat(parameters('factoryName'), '/S3LeapDataSet_Cloud3_File')]",
			"type": "Microsoft.DataFactory/factories/datasets",
			"apiVersion": "2018-06-01",
			"properties": {
				"linkedServiceName": {
					"referenceName": "Leap_AmazonS3",
					"type": "LinkedServiceReference"
				},
				"parameters": {
					"filename": {
						"type": "string"
					}
				},
				"folder": {
					"name": "FileConnection"
				},
				"annotations": [],
				"type": "Binary",
				"typeProperties": {
					"location": {
						"type": "AmazonS3Location",
						"bucketName": "leapdata-tas",
						"folderPath": "LEAP/Cloud3",
						"fileName": {
							"value": "@dataset().filename",
							"type": "Expression"
						}
					}
				}
			},
			"dependsOn": []
		},
		{
			"name": "[concat(parameters('factoryName'), '/S3LeapDataSet_Cloud3_Folder')]",
			"type": "Microsoft.DataFactory/factories/datasets",
			"apiVersion": "2018-06-01",
			"properties": {
				"linkedServiceName": {
					"referenceName": "Leap_AmazonS3",
					"type": "LinkedServiceReference"
				},
				"folder": {
					"name": "FileConnection"
				},
				"annotations": [],
				"type": "Binary",
				"typeProperties": {
					"location": {
						"type": "AmazonS3Location",
						"bucketName": "leapdata-tas",
						"folderPath": "LEAP/Cloud3"
					}
				}
			},
			"dependsOn": []
		},
		{
			"name": "[concat(parameters('factoryName'), '/S3TASOrderDataSet_Cloud1_File')]",
			"type": "Microsoft.DataFactory/factories/datasets",
			"apiVersion": "2018-06-01",
			"properties": {
				"linkedServiceName": {
					"referenceName": "Leap_AmazonS3",
					"type": "LinkedServiceReference"
				},
				"parameters": {
					"filename": {
						"type": "string"
					}
				},
				"folder": {
					"name": "TASOrders"
				},
				"annotations": [],
				"type": "DelimitedText",
				"typeProperties": {
					"location": {
						"type": "AmazonS3Location",
						"bucketName": "leapdata-tas",
						"folderPath": "LEAP/Cloud1/Log",
						"fileName": {
							"value": "@dataset().filename",
							"type": "Expression"
						}
					},
					"columnDelimiter": "|",
					"escapeChar": "\\",
					"firstRowAsHeader": true,
					"quoteChar": "\""
				},
				"schema": []
			},
			"dependsOn": []
		},
		{
			"name": "[concat(parameters('factoryName'), '/S3TASOrderDataSet_Cloud1_Folder')]",
			"type": "Microsoft.DataFactory/factories/datasets",
			"apiVersion": "2018-06-01",
			"properties": {
				"linkedServiceName": {
					"referenceName": "Leap_AmazonS3",
					"type": "LinkedServiceReference"
				},
				"parameters": {
					"Directory": {
						"type": "string"
					}
				},
				"folder": {
					"name": "TASOrders"
				},
				"annotations": [],
				"type": "Binary",
				"typeProperties": {
					"location": {
						"type": "AmazonS3Location",
						"bucketName": "leapdata-tas",
						"folderPath": {
							"value": "@dataset().Directory",
							"type": "Expression"
						}
					}
				}
			},
			"dependsOn": []
		},
		{
			"name": "[concat(parameters('factoryName'), '/S3TASOrderDataSet_Cloud2_File')]",
			"type": "Microsoft.DataFactory/factories/datasets",
			"apiVersion": "2018-06-01",
			"properties": {
				"linkedServiceName": {
					"referenceName": "Leap_AmazonS3",
					"type": "LinkedServiceReference"
				},
				"parameters": {
					"filename": {
						"type": "string"
					}
				},
				"folder": {
					"name": "TASOrders"
				},
				"annotations": [],
				"type": "DelimitedText",
				"typeProperties": {
					"location": {
						"type": "AmazonS3Location",
						"bucketName": "leapdata-tas",
						"folderPath": "LEAP/Cloud2/Log",
						"fileName": {
							"value": "@dataset().filename",
							"type": "Expression"
						}
					},
					"columnDelimiter": "|",
					"escapeChar": "\\",
					"firstRowAsHeader": true,
					"quoteChar": "\""
				},
				"schema": []
			},
			"dependsOn": []
		},
		{
			"name": "[concat(parameters('factoryName'), '/S3TASOrderDataSet_Cloud2_Folder')]",
			"type": "Microsoft.DataFactory/factories/datasets",
			"apiVersion": "2018-06-01",
			"properties": {
				"linkedServiceName": {
					"referenceName": "Leap_AmazonS3",
					"type": "LinkedServiceReference"
				},
				"parameters": {
					"Directory": {
						"type": "string"
					}
				},
				"folder": {
					"name": "TASOrders"
				},
				"annotations": [],
				"type": "Binary",
				"typeProperties": {
					"location": {
						"type": "AmazonS3Location",
						"bucketName": "leapdata-tas",
						"folderPath": {
							"value": "@dataset().Directory",
							"type": "Expression"
						}
					}
				}
			},
			"dependsOn": []
		},
		{
			"name": "[concat(parameters('factoryName'), '/S3TASOrderDataSet_Cloud3_File')]",
			"type": "Microsoft.DataFactory/factories/datasets",
			"apiVersion": "2018-06-01",
			"properties": {
				"linkedServiceName": {
					"referenceName": "Leap_AmazonS3",
					"type": "LinkedServiceReference"
				},
				"parameters": {
					"filename": {
						"type": "string"
					}
				},
				"folder": {
					"name": "TASOrders"
				},
				"annotations": [],
				"type": "DelimitedText",
				"typeProperties": {
					"location": {
						"type": "AmazonS3Location",
						"bucketName": "leapdata-tas",
						"folderPath": "LEAP/Cloud3/Log",
						"fileName": {
							"value": "@dataset().filename",
							"type": "Expression"
						}
					},
					"columnDelimiter": "|",
					"escapeChar": "\\",
					"firstRowAsHeader": true,
					"quoteChar": "\""
				},
				"schema": []
			},
			"dependsOn": []
		},
		{
			"name": "[concat(parameters('factoryName'), '/S3TASOrderDataSet_Cloud3_Folder')]",
			"type": "Microsoft.DataFactory/factories/datasets",
			"apiVersion": "2018-06-01",
			"properties": {
				"linkedServiceName": {
					"referenceName": "Leap_AmazonS3",
					"type": "LinkedServiceReference"
				},
				"parameters": {
					"Directory": {
						"type": "string"
					}
				},
				"folder": {
					"name": "TASOrders"
				},
				"annotations": [],
				"type": "Binary",
				"typeProperties": {
					"location": {
						"type": "AmazonS3Location",
						"bucketName": "leapdata-tas",
						"folderPath": {
							"value": "@dataset().Directory",
							"type": "Expression"
						}
					}
				}
			},
			"dependsOn": []
		},
		{
			"name": "[concat(parameters('factoryName'), '/SALES_NCS_table')]",
			"type": "Microsoft.DataFactory/factories/datasets",
			"apiVersion": "2018-06-01",
			"properties": {
				"linkedServiceName": {
					"referenceName": "PnGDataFoundation",
					"type": "LinkedServiceReference"
				},
				"folder": {
					"name": "DF_DBConnection/NCS Tables"
				},
				"annotations": [],
				"type": "AzureSqlTable",
				"schema": [
					{
						"name": "BRANCHCODE",
						"type": "varchar"
					},
					{
						"name": "DSECODE",
						"type": "varchar"
					},
					{
						"name": "CUSTCODE",
						"type": "varchar"
					},
					{
						"name": "INVNO",
						"type": "varchar"
					},
					{
						"name": "INVDATE",
						"type": "datetime2",
						"scale": 3
					},
					{
						"name": "SKUCCODE",
						"type": "varchar"
					},
					{
						"name": "SKUDCODE",
						"type": "varchar"
					},
					{
						"name": "SKUEANCODE",
						"type": "varchar"
					},
					{
						"name": "BATCHCODE",
						"type": "varchar"
					},
					{
						"name": "QTY",
						"type": "int",
						"precision": 10
					},
					{
						"name": "GROSSAMOUNT",
						"type": "decimal",
						"precision": 18,
						"scale": 2
					},
					{
						"name": "TAXAMOUNT",
						"type": "decimal",
						"precision": 18,
						"scale": 2
					},
					{
						"name": "INITDISC",
						"type": "decimal",
						"precision": 18,
						"scale": 2
					},
					{
						"name": "LINEDISC",
						"type": "decimal",
						"precision": 18,
						"scale": 2
					},
					{
						"name": "NETAMOUNT",
						"type": "decimal",
						"precision": 18,
						"scale": 2
					},
					{
						"name": "INVREF",
						"type": "varchar"
					},
					{
						"name": "SELECTEDDATE",
						"type": "datetime2",
						"scale": 3
					},
					{
						"name": "TIMESTAMP",
						"type": "datetime2",
						"scale": 3
					},
					{
						"name": "UPC",
						"type": "int",
						"precision": 10
					},
					{
						"name": "RETAILING",
						"type": "decimal",
						"precision": 18,
						"scale": 2
					},
					{
						"name": "BranchId",
						"type": "int",
						"precision": 10
					},
					{
						"name": "ProductId",
						"type": "int",
						"precision": 10
					},
					{
						"name": "FileSetId",
						"type": "int",
						"precision": 10
					},
					{
						"name": "flgProcess",
						"type": "tinyint",
						"precision": 3
					},
					{
						"name": "Filename",
						"type": "varchar"
					},
					{
						"name": "LastModifiedDatetime",
						"type": "smalldatetime",
						"precision": 16,
						"scale": 0
					},
					{
						"name": "TimeStampIns",
						"type": "smalldatetime",
						"precision": 16,
						"scale": 0
					}
				],
				"typeProperties": {
					"schema": "dbo",
					"table": "NC_SALES_Current"
				}
			},
			"dependsOn": []
		},
		{
			"name": "[concat(parameters('factoryName'), '/SALES_SUBD_NCS_table')]",
			"type": "Microsoft.DataFactory/factories/datasets",
			"apiVersion": "2018-06-01",
			"properties": {
				"linkedServiceName": {
					"referenceName": "PnGDataFoundation",
					"type": "LinkedServiceReference"
				},
				"folder": {
					"name": "DF_DBConnection/NCS Tables"
				},
				"annotations": [],
				"type": "AzureSqlTable",
				"schema": [
					{
						"name": "SUBDCODE",
						"type": "varchar"
					},
					{
						"name": "DSECODE",
						"type": "varchar"
					},
					{
						"name": "CUSTCODE",
						"type": "varchar"
					},
					{
						"name": "INVNO",
						"type": "varchar"
					},
					{
						"name": "INVDATE",
						"type": "datetime",
						"precision": 23,
						"scale": 3
					},
					{
						"name": "SKUCCODE",
						"type": "varchar"
					},
					{
						"name": "SKUDCODE",
						"type": "varchar"
					},
					{
						"name": "SKUEANCODE",
						"type": "varchar"
					},
					{
						"name": "BATCHCODE",
						"type": "varchar"
					},
					{
						"name": "QTY",
						"type": "int",
						"precision": 10
					},
					{
						"name": "GROSSAMOUNT",
						"type": "decimal",
						"precision": 18,
						"scale": 2
					},
					{
						"name": "TAXAMOUNT",
						"type": "decimal",
						"precision": 18,
						"scale": 2
					},
					{
						"name": "INITDISC",
						"type": "decimal",
						"precision": 18,
						"scale": 2
					},
					{
						"name": "LINEDISC",
						"type": "decimal",
						"precision": 18,
						"scale": 2
					},
					{
						"name": "NETAMOUNT",
						"type": "decimal",
						"precision": 18,
						"scale": 2
					},
					{
						"name": "INVREF",
						"type": "varchar"
					},
					{
						"name": "SELECTEDDATE",
						"type": "datetime",
						"precision": 23,
						"scale": 3
					},
					{
						"name": "TimeStamp",
						"type": "datetime",
						"precision": 23,
						"scale": 3
					},
					{
						"name": "UPC",
						"type": "int",
						"precision": 10
					},
					{
						"name": "RETAILING",
						"type": "decimal",
						"precision": 18,
						"scale": 2
					},
					{
						"name": "Filename",
						"type": "varchar"
					},
					{
						"name": "LastModifiedDatetime",
						"type": "smalldatetime",
						"precision": 16,
						"scale": 0
					},
					{
						"name": "TimeStampIns",
						"type": "smalldatetime",
						"precision": 16,
						"scale": 0
					}
				],
				"typeProperties": {
					"schema": "dbo",
					"table": "NC_SALES_SUBD_Current"
				}
			},
			"dependsOn": []
		},
		{
			"name": "[concat(parameters('factoryName'), '/SRN_NCS_table')]",
			"type": "Microsoft.DataFactory/factories/datasets",
			"apiVersion": "2018-06-01",
			"properties": {
				"linkedServiceName": {
					"referenceName": "PnGDataFoundation",
					"type": "LinkedServiceReference"
				},
				"folder": {
					"name": "DF_DBConnection/NCS Tables"
				},
				"annotations": [],
				"type": "AzureSqlTable",
				"schema": [
					{
						"name": "BRANCHCODE",
						"type": "varchar"
					},
					{
						"name": "DSECODE",
						"type": "varchar"
					},
					{
						"name": "CUSTCODE",
						"type": "varchar"
					},
					{
						"name": "SRNNO",
						"type": "varchar"
					},
					{
						"name": "INVNO",
						"type": "varchar"
					},
					{
						"name": "SRNDATE",
						"type": "datetime2",
						"scale": 3
					},
					{
						"name": "SKUCCODE",
						"type": "varchar"
					},
					{
						"name": "SKUDCODE",
						"type": "varchar"
					},
					{
						"name": "SKUEANCODE",
						"type": "varchar"
					},
					{
						"name": "BATCHCODE",
						"type": "varchar"
					},
					{
						"name": "QTY",
						"type": "int",
						"precision": 10
					},
					{
						"name": "SELECTEDDATE",
						"type": "datetime2",
						"scale": 3
					},
					{
						"name": "TIMESTAMP",
						"type": "datetime2",
						"scale": 3
					},
					{
						"name": "GROSSINVAMT",
						"type": "decimal",
						"precision": 18,
						"scale": 2
					},
					{
						"name": "NETINVAMT",
						"type": "decimal",
						"precision": 18,
						"scale": 2
					},
					{
						"name": "LINEDISC",
						"type": "decimal",
						"precision": 18,
						"scale": 2
					},
					{
						"name": "INITDISC",
						"type": "decimal",
						"precision": 18,
						"scale": 2
					},
					{
						"name": "TAXES",
						"type": "decimal",
						"precision": 18,
						"scale": 2
					},
					{
						"name": "UPC",
						"type": "int",
						"precision": 10
					},
					{
						"name": "RETAILING",
						"type": "decimal",
						"precision": 18,
						"scale": 2
					},
					{
						"name": "BranchId",
						"type": "int",
						"precision": 10
					},
					{
						"name": "ProductId",
						"type": "int",
						"precision": 10
					},
					{
						"name": "FileSetId",
						"type": "int",
						"precision": 10
					},
					{
						"name": "flgProcess",
						"type": "tinyint",
						"precision": 3
					},
					{
						"name": "Filename",
						"type": "varchar"
					},
					{
						"name": "LastModifiedDatetime",
						"type": "smalldatetime",
						"precision": 16,
						"scale": 0
					},
					{
						"name": "TimeStampIns",
						"type": "smalldatetime",
						"precision": 16,
						"scale": 0
					}
				],
				"typeProperties": {
					"schema": "dbo",
					"table": "NC_SRN_Current"
				}
			},
			"dependsOn": []
		},
		{
			"name": "[concat(parameters('factoryName'), '/SRN_SUBD_NCS_table')]",
			"type": "Microsoft.DataFactory/factories/datasets",
			"apiVersion": "2018-06-01",
			"properties": {
				"linkedServiceName": {
					"referenceName": "PnGDataFoundation",
					"type": "LinkedServiceReference"
				},
				"folder": {
					"name": "DF_DBConnection/NCS Tables"
				},
				"annotations": [],
				"type": "AzureSqlTable",
				"schema": [
					{
						"name": "SUBDCODE",
						"type": "varchar"
					},
					{
						"name": "DSECODE",
						"type": "varchar"
					},
					{
						"name": "CUSTCODE",
						"type": "varchar"
					},
					{
						"name": "SRNNO",
						"type": "varchar"
					},
					{
						"name": "INVNO",
						"type": "varchar"
					},
					{
						"name": "SRNDATE",
						"type": "datetime",
						"precision": 23,
						"scale": 3
					},
					{
						"name": "SKUCCODE",
						"type": "varchar"
					},
					{
						"name": "SKUDCODE",
						"type": "varchar"
					},
					{
						"name": "SKUEANCODE",
						"type": "varchar"
					},
					{
						"name": "BATCHCODE",
						"type": "varchar"
					},
					{
						"name": "QTY",
						"type": "int",
						"precision": 10
					},
					{
						"name": "SELECTEDDATE",
						"type": "datetime",
						"precision": 23,
						"scale": 3
					},
					{
						"name": "Timestamp",
						"type": "datetime",
						"precision": 23,
						"scale": 3
					},
					{
						"name": "GROSSINVAMT",
						"type": "decimal",
						"precision": 18,
						"scale": 2
					},
					{
						"name": "NETINVAMT",
						"type": "decimal",
						"precision": 18,
						"scale": 2
					},
					{
						"name": "LINEDISC",
						"type": "decimal",
						"precision": 18,
						"scale": 2
					},
					{
						"name": "INITDISC",
						"type": "decimal",
						"precision": 18,
						"scale": 2
					},
					{
						"name": "TAXES",
						"type": "decimal",
						"precision": 18,
						"scale": 2
					},
					{
						"name": "UPC",
						"type": "int",
						"precision": 10
					},
					{
						"name": "RETAILING",
						"type": "decimal",
						"precision": 18,
						"scale": 2
					},
					{
						"name": "Filename",
						"type": "varchar"
					},
					{
						"name": "LastModifiedDatetime",
						"type": "smalldatetime",
						"precision": 16,
						"scale": 0
					},
					{
						"name": "TimeStampIns",
						"type": "smalldatetime",
						"precision": 16,
						"scale": 0
					}
				],
				"typeProperties": {
					"schema": "dbo",
					"table": "NC_SRN_SUBD_Current"
				}
			},
			"dependsOn": []
		},
		{
			"name": "[concat(parameters('factoryName'), '/TASDBConnection')]",
			"type": "Microsoft.DataFactory/factories/datasets",
			"apiVersion": "2018-06-01",
			"properties": {
				"linkedServiceName": {
					"referenceName": "TASDatabase",
					"type": "LinkedServiceReference"
				},
				"folder": {
					"name": "DF_DBConnection"
				},
				"annotations": [],
				"type": "AzureSqlTable",
				"schema": [],
				"typeProperties": {}
			},
			"dependsOn": []
		},
		{
			"name": "[concat(parameters('factoryName'), '/TASDBConnection_Test')]",
			"type": "Microsoft.DataFactory/factories/datasets",
			"apiVersion": "2018-06-01",
			"properties": {
				"linkedServiceName": {
					"referenceName": "TASDatabase_Test",
					"type": "LinkedServiceReference"
				},
				"folder": {
					"name": "TASOrders"
				},
				"annotations": [],
				"type": "AzureSqlTable",
				"schema": [],
				"typeProperties": {}
			},
			"dependsOn": []
		},
		{
			"name": "[concat(parameters('factoryName'), '/TASK_table')]",
			"type": "Microsoft.DataFactory/factories/datasets",
			"apiVersion": "2018-06-01",
			"properties": {
				"linkedServiceName": {
					"referenceName": "TASDatabase",
					"type": "LinkedServiceReference"
				},
				"folder": {
					"name": "DF_DBConnection/LEAP Tables"
				},
				"annotations": [],
				"type": "AzureSqlTable",
				"schema": [
					{
						"name": "distributor_code",
						"type": "nvarchar"
					},
					{
						"name": "distributor_name",
						"type": "nvarchar"
					},
					{
						"name": "branch_code",
						"type": "nvarchar"
					},
					{
						"name": "branch_name",
						"type": "nvarchar"
					},
					{
						"name": "task_code",
						"type": "nvarchar"
					},
					{
						"name": "task_created_date",
						"type": "nvarchar"
					},
					{
						"name": "created_user_code",
						"type": "nvarchar"
					},
					{
						"name": "created_user_name",
						"type": "nvarchar"
					},
					{
						"name": "assigned_to",
						"type": "nvarchar"
					},
					{
						"name": "retailer_code",
						"type": "nvarchar"
					},
					{
						"name": "retailer_name",
						"type": "nvarchar"
					},
					{
						"name": "task_title",
						"type": "nvarchar"
					},
					{
						"name": "task_description",
						"type": "nvarchar"
					},
					{
						"name": "due_date",
						"type": "nvarchar"
					},
					{
						"name": "over_due",
						"type": "nvarchar"
					},
					{
						"name": "task_remark",
						"type": "nvarchar"
					},
					{
						"name": "task_status",
						"type": "nvarchar"
					},
					{
						"name": "tas_task_date",
						"type": "nvarchar"
					},
					{
						"name": "tas_task_id",
						"type": "nvarchar"
					},
					{
						"name": "tas_seller_code",
						"type": "nvarchar"
					},
					{
						"name": "tas_seller_name",
						"type": "nvarchar"
					},
					{
						"name": "FileSetId",
						"type": "bigint",
						"precision": 19
					},
					{
						"name": "Filename",
						"type": "varchar"
					},
					{
						"name": "LastModifiedDatetime",
						"type": "smalldatetime",
						"precision": 16,
						"scale": 0
					},
					{
						"name": "TimeStampIns",
						"type": "smalldatetime",
						"precision": 16,
						"scale": 0
					}
				],
				"typeProperties": {
					"schema": "dbo",
					"table": "tmpRawLEAPTAS_TASK"
				}
			},
			"dependsOn": []
		},
		{
			"name": "[concat(parameters('factoryName'), '/TASOrderDataSet_Cloud1_File')]",
			"type": "Microsoft.DataFactory/factories/datasets",
			"apiVersion": "2018-06-01",
			"properties": {
				"linkedServiceName": {
					"referenceName": "NCSdataStorageLink",
					"type": "LinkedServiceReference"
				},
				"parameters": {
					"filename": {
						"type": "string"
					}
				},
				"folder": {
					"name": "TASOrders"
				},
				"annotations": [],
				"type": "DelimitedText",
				"typeProperties": {
					"location": {
						"type": "AzureBlobStorageLocation",
						"fileName": {
							"value": "@dataset().filename",
							"type": "Expression"
						},
						"folderPath": "Cloud01",
						"container": "ncsstorage"
					},
					"columnDelimiter": ",",
					"escapeChar": "\\",
					"firstRowAsHeader": true,
					"quoteChar": "\""
				},
				"schema": []
			},
			"dependsOn": []
		},
		{
			"name": "[concat(parameters('factoryName'), '/TASOrderLogStorageDS')]",
			"type": "Microsoft.DataFactory/factories/datasets",
			"apiVersion": "2018-06-01",
			"properties": {
				"linkedServiceName": {
					"referenceName": "NCSdataStorageLink",
					"type": "LinkedServiceReference"
				},
				"parameters": {
					"Directory": {
						"type": "string"
					}
				},
				"folder": {
					"name": "TASOrders"
				},
				"annotations": [],
				"type": "DelimitedText",
				"typeProperties": {
					"location": {
						"type": "AzureBlobStorageLocation",
						"folderPath": {
							"value": "@dataset().Directory",
							"type": "Expression"
						},
						"container": "tasorderlog"
					},
					"columnDelimiter": "|",
					"escapeChar": "\\",
					"quoteChar": "\""
				},
				"schema": []
			},
			"dependsOn": []
		},
		{
			"name": "[concat(parameters('factoryName'), '/TASOrderLogStorageDataset')]",
			"type": "Microsoft.DataFactory/factories/datasets",
			"apiVersion": "2018-06-01",
			"properties": {
				"linkedServiceName": {
					"referenceName": "NCSdataStorageLink",
					"type": "LinkedServiceReference"
				},
				"parameters": {
					"Directory": {
						"type": "string"
					}
				},
				"folder": {
					"name": "StagingSource"
				},
				"annotations": [],
				"type": "Binary",
				"typeProperties": {
					"location": {
						"type": "AzureBlobStorageLocation",
						"folderPath": {
							"value": "@dataset().Directory",
							"type": "Expression"
						},
						"container": "tasorderlog"
					}
				}
			},
			"dependsOn": []
		}
	]
}